PKG/pkg.v
`ifndef PKG
`define PKG
	
	//Operations
	`define OPP_WIDTH 8

	`define NO_OPP 	0
	`define FETCH   1
	`define LOAD 	2
	`define STORE	4
	`define SUM 	8
	`define AND 	16
	`define OR  	32
	`define XOR 	64
	`define SR  	128


	//Hardware Definitions
	`define REG_WIDTH 8
	`define INSTRUCTION_WIDTH 8
	`define ADDR_WIDTH 16

	//ALU MUX Reg Selectors
	`define SELECTOR_PC 	0
	`define SELECTOR_ADD 	1
	`define SELECTOR_X		2
	`define SELECTOR_Y 		3
	`define SELECTOR_IMM    4

	//STATUS REG Bit Definitions
	`define CARRY       1
	`define ZERO       	2
	`define INT_DIS  	4
	`define DEC      	8
	`define BREAK    	16
	`define V_OVERFLOW	64
	`define NEG			128

	//Opp Code
	`define OPP_SPECIAL 5'bXXX_00 //LB 0, 4, 8, C
	`define OPP_ILLEGAL 5'bXXX_11 //LB 3, 7, B, F

	`define	OPP_ORA 	5'b000_01
	`define OPP_ASL		5'b000_10
	`define OPP_AND		5'b001_01
	`define OPP_ROL		5'b001_10
	`define OPP_EOR		5'b010_01
	`define OPP_LSR		5'b010_10
	`define OPP_ADC		5'b011_01
	`define OPP_ROR		5'b011_10
	`define OPP_STA		5'b100_01
	`define OPP_STX		5'b100_10
	`define OPP_LDA		5'b101_01
	`define OPP_LDX		5'b101_10
	`define OPP_CMP		5'b110_01
	`define OPP_DEC		5'b110_10
	`define OPP_SBC		5'b111_01
	`define OPP_INC		5'b111_10

	//Spec Opp Codes 6 bits (instruction [7:2])
	//There is probably a cleaner way to encode these
	`define SPEC_OPP_BRK 	6'b0000_00
	`define SPEC_OPP_BPL	6'b0001_00
	//...

	//Address Modes
	`define AM3_X_IND	3'b000 
	`define AM3_ZPG		3'b001
	`define AM3_IMM		3'b010
	`define AM3_ABS		3'b011
	`define AM3_IND_Y	3'b100
	`define AM3_ZPG_X	3'b101
	`define AM3_ABS_Y	3'b110
	`define AM3_ABS_X	3'b111

`include "Design/mux831.v"
`include "Design/register.v"
`include "Design/clock_module.v"
`include "Design/ALU.v"
`include "Design/6502_top.v"
`include "Design/decoder.v"

`endif

PKG/test_program_macros.v
//Sam Baker
//07/2023

//Instruction sets for test benches
//Macros will give instructions and expected modifications to mem

`ifndef INST_MACROS
`define INST_MACROS

`define MEM_DEPTH           'h01FF 
`define INSTRUCTION_BASE    'h0150

//`define MEM_DEPTH           16'h00FF 
//`define INSTRUCTION_BASE    16'h0050

//Blank test for checking build
`define TEST_NOOPP          inst_list[0]    = 8'h00;        \     
                            inst_list[1]    = 8'h00;        \
                            inst_list[2]    = 8'h00;        \     
                            inst_list[3]    = 8'h00;        \
                            inst_list[4]    = 8'h00;        \  
                            inst_list[5]    = 8'h00;        \
                            inst_list[6]    = 8'h00;        \
                            inst_list[7]    = 8'h00;        \
                            inst_list[8]    = 8'h00;        \
                            inst_list[9]    = 8'h00;        \
                            inst_list[10]   = 8'h00;        \    
                            inst_list[11]   = 8'h00;        \
                            inst_list[12]   = 8'h00;        \
                            inst_list[13]   = 8'h00;        \
                            inst_list[14]   = 8'h00;        \
                            inst_list[15]   = 8'h00;        \
                                                            \
                            mem_model[16'h02] = mem_model[16'h02];      \
                            mem_model[16'h0C] = mem_model[16'h0C];      \
                            mem_model[16'h08] = mem_model[16'h08];      \
                            mem_model[16'h06] = mem_model[16'h06];


`define TEST_LDAZPG         inst_list[0]    = 8'hA9;        \   //  LDA #   
                            inst_list[1]    = 8'h04;        \   //  x04
                            inst_list[2]    = 8'h85;        \   //  STA ZPG 
                            inst_list[3]    = 8'h02;        \   //  x02
                            inst_list[4]    = 8'hA5;        \   //  LDA ZPG
                            inst_list[5]    = 8'h0A;        \   //  x0A
                            inst_list[6]    = 8'h85;        \   //  STA ZPG
                            inst_list[7]    = 8'h04;        \   //  x04
                            inst_list[8]    = 8'hA2;        \   //  LDX # 101 000 10
                            inst_list[9]    = 8'h01;        \   //  x01   101 000 01
                            inst_list[10]   = 8'hB5;        \   //  LDA ZPG_X 
                            inst_list[11]   = 8'h05;        \   //  x05
                            inst_list[12]   = 8'h85;        \   //  STA ZPG
                            inst_list[13]   = 8'h08;        \   //  x08
                            inst_list[14]   = 8'h86;        \   //  STX ZPG
                            inst_list[15]   = 8'h0A;        \   //  x0A
                                                            \
                            mem_model[16'h02] = 8'h04;      \
                            mem_model[16'h04] = mem_model[16'h0A];      \
                            mem_model[16'h08] = mem_model[16'h06];      \
                            mem_model[16'h0A] = 8'h01;

// Test ABS LDA and STA, Note MEM must be at least 'h015f for this test
`define TEST_LDAABS         inst_list[0]    = 8'hAD;        \   //  LDA ABS   
                            inst_list[1]    = 8'h4f;        \   //  x4f
                            inst_list[2]    = 8'h01;        \   //  x01
                            inst_list[3]    = 8'h8D;        \   //  STA ABS
                            inst_list[4]    = 8'h41;        \   //  x41
                            inst_list[5]    = 8'h01;        \   //  x01
                            inst_list[6]    = 8'hA2;        \   //  LDX #
                            inst_list[7]    = 8'h0A;        \   //  x0A
                            inst_list[8]    = 8'hBD;        \   //  LDA ABS_X 
                            inst_list[9]    = 8'hFF;        \   //  x40
                            inst_list[10]   = 8'h00;        \   //  x01      //     x0145
                            inst_list[11]   = 8'hA2;        \   //  LDX #
                            inst_list[12]   = 8'h03;        \   //  x03
                            inst_list[13]   = 8'h9D;        \   //  STA ABS_X
                            inst_list[14]   = 8'h41;        \   //  x41
                            inst_list[15]   = 8'h01;        \   //  x01      //     x0144
                                                            \
                            inst_list[16]   = 8'hA0;        \   //  LDY #
                            inst_list[17]   = 8'h02;        \   //  x0A
                            inst_list[18]   = 8'hB9;        \   //  LDA ABS_Y 
                            inst_list[19]   = 8'hFF;        \   //  xFF
                            inst_list[20]   = 8'h00;        \   //  x00      //     x0145
                            inst_list[21]   = 8'hA0;        \   //  LDY #
                            inst_list[22]   = 8'h03;        \   //  x03
                            inst_list[23]   = 8'h99;        \   //  STA ABS_Y
                            inst_list[24]   = 8'hFF;        \   //  xFF
                            inst_list[25]   = 8'h00;        \   //  x00      //     x0144
                                                            \
                            mem_model[16'h0141] = mem_model[16'h014f];      \
                            mem_model[16'h0144] = mem_model[16'h0109];      \
                            mem_model[16'h0102] = mem_model[16'h0101];

`define TEST_LDYSTY         inst_list[0]    = 8'hA0;        \   //  LDY #   
                            inst_list[1]    = 8'hFF;        \   //  xFF
                            inst_list[2]    = 8'h84;        \   //  STY ZPG
                            inst_list[3]    = 8'h0A;        \   //  x0A
                                                            \
                            mem_model[16'h000A] = 8'hff;    


// X_IND and IND_Y, Note MEM must be at least 'h015f for this test
`define TEST_INDXY          inst_list[0]    = 8'hA9;        \   //  LDA #   
                            inst_list[1]    = 8'hFF;        \   //  xFF
                            inst_list[2]    = 8'h8D;        \   //  STA ABS
                            inst_list[3]    = 8'h41;        \   //  x41
                            inst_list[4]    = 8'h01;        \   //  x01
                            inst_list[5]    = 8'hA9;        \   //  LDA #   
                            inst_list[6]    = 8'h00;        \   //  x00
                            inst_list[7]    = 8'h8D;        \   //  STA ABS
                            inst_list[8]    = 8'h42;        \   //  x42
                            inst_list[9]    = 8'h01;        \   //  x01
                                                            \
                            inst_list[10]    = 8'hA9;        \   //  LDA #   
                            inst_list[11]    = 8'h30;        \   //  x30
                            inst_list[12]    = 8'h8D;        \   //  STA ABS
                            inst_list[13]    = 8'h24;        \   //  x24
                            inst_list[14]    = 8'h01;        \   //  x01
                            inst_list[15]    = 8'hA9;        \   //  LDA #   
                            inst_list[16]    = 8'h01;        \   //  x01
                            inst_list[17]    = 8'h8D;        \   //  STA ABS
                            inst_list[18]    = 8'h25;        \   //  x25
                            inst_list[19]    = 8'h01;        \   //  x01
                            \                                  
                            inst_list[20]    = 8'hA2;        \   //  LDX #   
                            inst_list[21]    = 8'h04;        \   //  x04
                            inst_list[22]    = 8'hA0;        \   //  LDY #
                            inst_list[23]    = 8'h0A;        \   //  x0A
                            inst_list[24]    = 8'hA1;        \   //  LDA X_IND 101 000 01
                            inst_list[25]    = 8'h20;        \   //  x20  
                            inst_list[26]    = 8'h01;        \   //  x01
                            inst_list[27]    = 8'h91;        \   //  STA IND_Y   100  100  01
                            inst_list[28]    = 8'h41;        \   //  8'h41
                            inst_list[29]    = 8'h01;        \   //  8'h01
                            \
                            test_carry = 1'b0;              \
                            \
                            mem_model[16'h0141] = 8'hFF;      \
                            mem_model[16'h0142] = 8'h00;      \
                            mem_model[16'h0124] = 8'h30;      \
                            mem_model[16'h0125] = 8'h01;      \
                            mem_model[16'h0109] = mem_model[16'h0130];


`define TEST_ADC            inst_list[0]    = 8'hA9;        \   //  LDA #   
                            inst_list[1]    = 8'h04;        \   //  x04
                            inst_list[2]    = 8'h69;        \   //  ADC # 
                            inst_list[3]    = 8'h02;        \   //  x02
                            inst_list[4]    = 8'h85;        \   //  STA ZPG 
                            inst_list[5]    = 8'h03;        \   //  x03
                                                            \
                            inst_list[6]    = 8'hA9;        \   //  LDA #   
                            inst_list[7]    = 8'hFF;        \   //  xFF
                            inst_list[8]    = 8'h69;        \   //  ADC # 
                            inst_list[9]    = 8'h02;        \   //  x01
                            inst_list[10]   = 8'h85;        \   //  STA ZPG 
                            inst_list[11]   = 8'h04;        \   //  x04
                                                            \
                            inst_list[12]    = 8'hA9;        \   //  LDA #   
                            inst_list[13]    = 8'h03;        \   //  x03
                            inst_list[14]    = 8'h69;        \   //  ADC # 
                            inst_list[15]    = 8'h03;        \   //  x03
                            inst_list[16]   = 8'h85;        \   //  STA ZPG 
                            inst_list[17]   = 8'h05;        \   //  x05
                                                            \
                            test_carry = 1'b0;              \
                                                            \
                            mem_model[16'h0003] = 8'h06;    \
                            mem_model[16'h0004] = 8'h01;    \
                            mem_model[16'h0005] = 8'h06;      


`define TEST_ALU_LOG        inst_list[0]    = 8'hA9;        \   //  LDA #   
                            inst_list[1]    = 8'h04;        \   //  x04
                            inst_list[2]    = 8'h69;        \   //  ADC # 
                            inst_list[3]    = 8'h02;        \   //  x02
                            inst_list[4]    = 8'h85;        \   //  STA ZPG 
                            inst_list[5]    = 8'h03;        \   //  x03
                            \
                            inst_list[6]    = 8'h09;        \   //  ORA #
                            inst_list[7]    = 8'h4A;        \   //  x01
                            inst_list[8]    = 8'h85;        \   //  STA ZPG 
                            inst_list[9]    = 8'h04;        \   //  x04
                            \
                            inst_list[10]   = 8'h29;        \   //  AND #
                            inst_list[11]   = 8'h55;        \   //  x55
                            inst_list[12]   = 8'h85;        \   //  STA ZPG 
                            inst_list[13]   = 8'h05;        \   //  x05
                            \                                                                                                                       
                            inst_list[14]   = 8'h49;        \   //  EOR #
                            inst_list[15]   = 8'h0F;        \   //  x0F
                            inst_list[16]   = 8'h85;        \   //  STA ZPG 
                            inst_list[17]   = 8'h06;        \   //  x06
                            \
                            mem_model[16'h0003] = 8'h06;                            \
                            mem_model[16'h0004] = (mem_model[16'h0003]   |   8'h4A);  \
                            mem_model[16'h0005] = (mem_model[16'h0004]   &   8'h55);  \
                            mem_model[16'h0006] = (mem_model[16'h0005]   ^   8'h0F);  

`define TEST_ALU_ASL        inst_list[0]    = 8'hA9;        \   //  LDA #   
                            inst_list[1]    = 8'hA4;        \   //  xA4
                            inst_list[2]    = 8'h0A;        \   //  ASL A 0A - 000 010 10
                            inst_list[3]    = 8'h85;        \   //  STA ZPG 
                            inst_list[4]    = 8'h03;        \   //  x03
                                                            \
                            test_carry = 1'b1;              \
                                                            \
                            mem_model[16'h0003] = (8'hA4 << 1); // 10100100 << 1 = 01001000 = 48
 
`define TEST_ALU_LSR        inst_list[0]    = 8'hA9;        \   //  LDA #   
                            inst_list[1]    = 8'hA1;        \   //  xA4
                            inst_list[2]    = 8'h4A;        \   //  LSR A 
                            inst_list[3]    = 8'h85;        \   //  STA ZPG 1000 0101
                            inst_list[4]    = 8'h03;        \   //  x03     00 1010 0001
                                                            \
                            test_carry = 1'b1;              \
                                                            \
                            mem_model[16'h0003] = (8'hA1 >> 1); 

//NOT DONE
`define TEST_ALU_INC        inst_list[0]    = 8'hA2;        \   //  LDX #   
                            inst_list[1]    = 8'hA4;        \   //  xA4
                            inst_list[2]    = 8'hE8;        \   //  INX 
                            inst_list[3]    = 8'h85;        \   //  STA ZPG 
                            inst_list[4]    = 8'h03;        \   //  x03
                                                            \
                            inst_list[5]    = 8'hA0;        \   //  LDY #   
                            inst_list[6]    = 8'hA1;        \   //  xA4
                            inst_list[7]    = 8'hC8;        \   //  INY 
                            inst_list[8]    = 8'h85;        \   //  STA ZPG 
                            inst_list[9]    = 8'h04;        \   //  x03
                                                            \
                            inst_list[10]    = 8'hE6;        \   //  INC ZPG
                            inst_list[11]    = 8'h04;        \   //  x04  
                            inst_list[12]    = 8'h85;        \   //  STA ZPG 
                            inst_list[13]    = 8'h05;        \   //  x03
                                                            \        
                            test_carry = 1'b0;              \
                                                            \
                            mem_model[16'h0003] = (8'hA4 + 1);     \
                            mem_model[16'h0004] = (8'hA1 + 1);     \
                            mem_model[16'h0005] = (mem_model[16'h0004] + 1);  

`endif

Design/ALU.v
//Sam Baker
//07/2023
//6502 ALU module

`ifndef ALU
`define ALU

module ALU(
	input phi1, phi2, reset_n,	
		
	input [`REG_WIDTH - 1 : 0] a, 
	input [`REG_WIDTH - 1 : 0] b, 
	input [`OPP_WIDTH - 1 : 0] func, 
	input carry_in,
	input dec_mode, 
	
	output reg [`REG_WIDTH - 1 : 0] dout, //douter hold register
	output reg [`REG_WIDTH - 1 : 0] status,
	output reg wout,
	output reg wout_status,
	output overflow,
	output reg carry_out,
	output half_carry
	);
	
	//In the 6502 most of this logic is implemented with NANDs and NORs but Im not pressed about it
	always @(posedge phi1) begin
		if (!reset_n) begin
			dout = 8'h00;
		end else if (func == `SUM) begin
			if (carry_in)						//I know it's wierd, don't ask
				{carry_out, dout} = a + b + 1;	//This is lazy but it'll do for now
			else
				{carry_out, dout} = a + b;
			wout = 1'b1;
		end else if (func == `AND) begin
			dout = a&b;	
			wout = 1'b1;
		end else if (func == `OR) begin
			dout = a|b;		
			wout = 1'b1;
		end else if (func == `XOR) begin
			dout = ~(a & b) & (a | b);	
			wout = 1'b1;
		end else if (func == `SR) begin
			dout = a << b;		
			wout = 1'b1;
		end else begin
			dout = 8'hZZ;
			wout = 1'b0;
		end
		
	end
endmodule

`endif

DV/tb_ALU.sv
//This is a testbench
`ifndef TB_ALU
`define TB_ALU

`timescale 1ns/1ns
`include "PKG/test_program_macros.v"
`include "PKG/pkg.v"


`define SEED   		33551
`define CYCLES 		30

module tb_alu;
    	reg phi1, phi2, reset_n;	
		
	    reg [`REG_WIDTH - 1 : 0] a; 
	    reg [`REG_WIDTH - 1 : 0] b; 
	    reg [`OPP_WIDTH - 1 : 0] func; 
	    reg carry_in;
	    reg dec_mode; 
	
	    wire [`REG_WIDTH - 1 : 0] add; 
	    wire [`REG_WIDTH - 1 : 0] status;
	    wire wout;
	    wire wout_status;
	    wire overflow;
	    wire carry_out;
	    wire half_carry;

		reg [31:0] seed, i, j;

	ALU alu(.reset_n(reset_n), 
			.phi1(phi1),
			.phi2(phi2),
			.func(func), 
			.carry_in(carry_in),
			.a(a), 
			.b(b), 
			.dout(add),
			.wout(wout),
			.carry_out(carry_out)
			);

	initial begin
		phi1 = 1'b0;
        phi2 = 1'b1;
		forever begin
			#1; 
            phi1 = ~phi1;
            phi2 = ~phi2;
		end
	end

	initial begin
		$dumpfile("Out/ALU.vcd");
		$dumpvars(0, tb_alu);

		seed = `SEED;

		reset_n = 1'b1;
		#4;
		reset_n = 1'b0;
		#4;
		reset_n = 1'b1;
		#4;

		for (i = 0; i < `CYCLES; i++) begin
			$display("New cycle %0d", i);
			for (j = 0; j < 6; j++) begin

				func = `REG_WIDTH'b1 << j;

				carry_in = $urandom(seed);
				a = $urandom(seed);
				b = $urandom(seed);
				//$display("X = %0d, Y = %0d, Opp = %b, j = %0d", a, b, opp, j);

				#10;
				case (func)
					`SUM: begin
						$display("%0h + %0h + %0d = %0h %h", a, b, carry_in, carry_out, add);
						if ((add + carry_out*9'h100) != (a + b + carry_in)) $fatal(1, "Sum operation incorrect");
					end
					`AND: begin
						$display("%0h & %0h = %0h", a, b, add);
						if (add != (a & b)) $fatal(1, "And operation incorrect");
					end
					`OR: begin
						$display("%0h | %0h = %0h", a, b, add);
						if (add != (a | b)) $fatal(1, "Or operation incorrect");
					end
					`XOR: begin
						$display("%0h ^ %0h = %0h", a, b, add);
						if (add != (a ^ b)) $fatal(1, "Xor operation incorrect");
					end
					`SR: begin
						$display("%0h << %0h = %0h", a, b, add);
						if (add != (a << b)) $fatal(1, "Sr operation incorrect");
					end
				endcase
				#10;
			end
		end

		$finish;
	end

endmodule

`endif

Out/ALU.vcd
$date
	Wed Aug 02 15:18:47 2023
$end
$version
	Icarus Verilog
$end
$timescale
	1ns
$end
$scope module tb_alu $end
$var wire 1 ! wout $end
$var wire 1 " carry_out $end
$var wire 8 # add [7:0] $end
$var reg 8 $ a [7:0] $end
$var reg 8 % b [7:0] $end
$var reg 1 & carry_in $end
$var reg 8 ' func [7:0] $end
$var reg 32 ( i [31:0] $end
$var reg 32 ) j [31:0] $end
$var reg 1 * phi1 $end
$var reg 1 + phi2 $end
$var reg 1 , reset_n $end
$var reg 32 - seed [31:0] $end
$scope module alu $end
$var wire 8 . a [7:0] $end
$var wire 8 / b [7:0] $end
$var wire 1 & carry_in $end
$var wire 1 0 dec_mode $end
$var wire 8 1 func [7:0] $end
$var wire 1 2 half_carry $end
$var wire 1 3 overflow $end
$var wire 1 * phi1 $end
$var wire 1 + phi2 $end
$var wire 1 , reset_n $end
$var reg 1 " carry_out $end
$var reg 8 4 dout [7:0] $end
$var reg 8 5 status [7:0] $end
$var reg 1 ! wout $end
$var reg 1 6 wout_status $end
$upscope $end
$upscope $end
$enddefinitions $end
$comment Show the parameter values. $end
$dumpall
$end
#0
$dumpvars
x6
bx 5
bx 4
z3
z2
bx 1
z0
bx /
bx .
b1000001100001111 -
1,
1+
0*
bx )
bx (
bx '
x&
bx %
bx $
bx #
x"
x!
$end
#1
0!
bz #
bz 4
0+
1*
#2
1+
0*
#3
0+
1*
#4
1+
0*
0,
#5
b0 #
b0 4
0+
1*
#6
1+
0*
#7
0+
1*
#8
1+
0*
1,
#9
bz #
bz 4
0+
1*
#10
1+
0*
#11
0+
1*
#12
1+
0*
b1111100 %
b1111100 /
b11011011 $
b11011011 .
0&
b10111110010110110000110001110010 -
b1 '
b1 1
b0 )
b0 (
#13
0+
1*
#14
1+
0*
#15
0+
1*
#16
1+
0*
#17
0+
1*
#18
1+
0*
#19
0+
1*
#20
1+
0*
#21
0+
1*
#22
1+
0*
#23
0+
1*
#24
1+
0*
#25
0+
1*
#26
1+
0*
#27
0+
1*
#28
1+
0*
#29
0+
1*
#30
1+
0*
#31
0+
1*
#32
1+
0*
b11110010 %
b11110010 /
b1100111 $
b1100111 .
1&
b1111001010111001001010011010001 -
b10 '
b10 1
b1 )
#33
0+
1*
#34
1+
0*
#35
0+
1*
#36
1+
0*
#37
0+
1*
#38
1+
0*
#39
0+
1*
#40
1+
0*
#41
0+
1*
#42
1+
0*
#43
0+
1*
#44
1+
0*
#45
0+
1*
#46
1+
0*
#47
0+
1*
#48
1+
0*
#49
0+
1*
#50
1+
0*
#51
0+
1*
#52
1+
0*
b101001 %
b101001 /
b1000000 $
b1000000 .
b10010100100111100111100011011100 -
b100 '
b100 1
b10 )
#53
0+
1*
#54
1+
0*
#55
0+
1*
#56
1+
0*
#57
0+
1*
#58
1+
0*
#59
0+
1*
#60
1+
0*
#61
0+
1*
#62
1+
0*
#63
0+
1*
#64
1+
0*
#65
0+
1*
#66
1+
0*
#67
0+
1*
#68
1+
0*
#69
0+
1*
#70
1+
0*
#71
0+
1*
#72
1+
0*
b111011 %
b111011 /
b11101001 $
b11101001 .
b10011101110110011110011100000011 -
b1000 '
b1000 1
b11 )
#73
1!
1"
b100101 #
b100101 4
0+
1*
#74
1+
0*
#75
0+
1*
#76
1+
0*
#77
0+
1*
#78
1+
0*
#79
0+
1*
#80
1+
0*
#81
0+
1*
#82
1+
0*
#83
0+
1*
#84
1+
0*
#85
0+
1*
#86
1+
0*
#87
0+
1*
#88
1+
0*
#89
0+
1*
#90
1+
0*
#91
0+
1*
#92
1+
0*
b10111010 %
b10111010 /
b11101010 $
b11101010 .
0&
b11011101001010101101001001110110 -
b10000 '
b10000 1
b100 )
#93
b10101010 #
b10101010 4
0+
1*
#94
1+
0*
#95
0+
1*
#96
1+
0*
#97
0+
1*
#98
1+
0*
#99
0+
1*
#100
1+
0*
#101
0+
1*
#102
1+
0*
#103
0+
1*
#104
1+
0*
#105
0+
1*
#106
1+
0*
#107
0+
1*
#108
1+
0*
#109
0+
1*
#110
1+
0*
#111
0+
1*
#112
1+
0*
b1110011 %
b1110011 /
b11010010 $
b11010010 .
b111001101011010010001000100101 -
b100000 '
b100000 1
b101 )
#113
b11110011 #
b11110011 4
0+
1*
#114
1+
0*
#115
0+
1*
#116
1+
0*
#117
0+
1*
#118
1+
0*
#119
0+
1*
#120
1+
0*
#121
0+
1*
#122
1+
0*
#123
0+
1*
#124
1+
0*
#125
0+
1*
#126
1+
0*
#127
0+
1*
#128
1+
0*
#129
0+
1*
#130
1+
0*
#131
0+
1*
#132
1+
0*
b1010010 %
b1010010 /
b10100110 $
b10100110 .
1&
b101001001000011100101111000000 -
b1 '
b1 1
b1 (
b0 )
#133
0!
bz #
bz 4
0+
1*
#134
1+
0*
#135
0+
1*
#136
1+
0*
#137
0+
1*
#138
1+
0*
#139
0+
1*
#140
1+
0*
#141
0+
1*
#142
1+
0*
#143
0+
1*
#144
1+
0*
#145
0+
1*
#146
1+
0*
#147
0+
1*
#148
1+
0*
#149
0+
1*
#150
1+
0*
#151
0+
1*
#152
1+
0*
b11010110 %
b11010110 /
b1101000 $
b1101000 .
0&
b1101011001011110100101010110111 -
b10 '
b10 1
b1 )
#153
0+
1*
#154
1+
0*
#155
0+
1*
#156
1+
0*
#157
0+
1*
#158
1+
0*
#159
0+
1*
#160
1+
0*
#161
0+
1*
#162
1+
0*
#163
0+
1*
#164
1+
0*
#165
0+
1*
#166
1+
0*
#167
0+
1*
#168
1+
0*
#169
0+
1*
#170
1+
0*
#171
0+
1*
#172
1+
0*
b11100100 %
b11100100 /
b1010011 $
b1010011 .
b1110010001110011010001100111010 -
b100 '
b100 1
b10 )
#173
0+
1*
#174
1+
0*
#175
0+
1*
#176
1+
0*
#177
0+
1*
#178
1+
0*
#179
0+
1*
#180
1+
0*
#181
0+
1*
#182
1+
0*
#183
0+
1*
#184
1+
0*
#185
0+
1*
#186
1+
0*
#187
0+
1*
#188
1+
0*
#189
0+
1*
#190
1+
0*
#191
0+
1*
#192
1+
0*
b1001100 %
b1001100 /
b10100000 $
b10100000 .
1&
b10100110001101011110000100111001 -
b1000 '
b1000 1
b11 )
#193
1!
0"
b11101101 #
b11101101 4
0+
1*
#194
1+
0*
#195
0+
1*
#196
1+
0*
#197
0+
1*
#198
1+
0*
#199
0+
1*
#200
1+
0*
#201
0+
1*
#202
1+
0*
#203
0+
1*
#204
1+
0*
#205
0+
1*
#206
1+
0*
#207
0+
1*
#208
1+
0*
#209
0+
1*
#210
1+
0*
#211
0+
1*
#212
1+
0*
b11000010 %
b11000010 /
b111000 $
b111000 .
b1100001011011111100001101100100 -
b10000 '
b10000 1
b100 )
#213
b0 #
b0 4
0+
1*
#214
1+
0*
#215
0+
1*
#216
1+
0*
#217
0+
1*
#218
1+
0*
#219
0+
1*
#220
1+
0*
#221
0+
1*
#222
1+
0*
#223
0+
1*
#224
1+
0*
#225
0+
1*
#226
1+
0*
#227
0+
1*
#228
1+
0*
#229
0+
1*
#230
1+
0*
#231
0+
1*
#232
1+
0*
b10011001 %
b10011001 /
b1110010 $
b1110010 .
b11001100100100100000001000101011 -
b100000 '
b100000 1
b101 )
#233
b11111011 #
b11111011 4
0+
1*
#234
1+
0*
#235
0+
1*
#236
1+
0*
#237
0+
1*
#238
1+
0*
#239
0+
1*
#240
1+
0*
#241
0+
1*
#242
1+
0*
#243
0+
1*
#244
1+
0*
#245
0+
1*
#246
1+
0*
#247
0+
1*
#248
1+
0*
#249
0+
1*
#250
1+
0*
#251
0+
1*
#252
1+
0*
b11101000 %
b11101000 /
b110 $
b110 .
0&
b1110100001011100110001010111110 -
b1 '
b1 1
b10 (
b0 )
#253
0!
bz #
bz 4
0+
1*
#254
1+
0*
#255
0+
1*
#256
1+
0*
#257
0+
1*
#258
1+
0*
#259
0+
1*
#260
1+
0*
#261
0+
1*
#262
1+
0*
#263
0+
1*
#264
1+
0*
#265
0+
1*
#266
1+
0*
#267
0+
1*
#268
1+
0*
#269
0+
1*
#270
1+
0*
#271
0+
1*
#272
1+
0*
b10001010 %
b10001010 /
b1101100 $
b1101100 .
1&
b11000101001111101000011000001101 -
b10 '
b10 1
b1 )
#273
0+
1*
#274
1+
0*
#275
0+
1*
#276
1+
0*
#277
0+
1*
#278
1+
0*
#279
0+
1*
#280
1+
0*
#281
0+
1*
#282
1+
0*
#283
0+
1*
#284
1+
0*
#285
0+
1*
#286
1+
0*
#287
0+
1*
#288
1+
0*
#289
0+
1*
#290
1+
0*
#291
0+
1*
#292
1+
0*
b11001100 %
b11001100 /
b11010010 $
b11010010 .
b11100110000011010010001111001000 -
b100 '
b100 1
b10 )
#293
0+
1*
#294
1+
0*
#295
0+
1*
#296
1+
0*
#297
0+
1*
#298
1+
0*
#299
0+
1*
#300
1+
0*
#301
0+
1*
#302
1+
0*
#303
0+
1*
#304
1+
0*
#305
0+
1*
#306
1+
0*
#307
0+
1*
#308
1+
0*
#309
0+
1*
#310
1+
0*
#311
0+
1*
#312
1+
0*
b10011 %
b10011 /
b100110 $
b100110 .
0&
b1001100001010010000101011111 -
b1000 '
b1000 1
b11 )
#313
1!
b111001 #
b111001 4
0+
1*
#314
1+
0*
#315
0+
1*
#316
1+
0*
#317
0+
1*
#318
1+
0*
#319
0+
1*
#320
1+
0*
#321
0+
1*
#322
1+
0*
#323
0+
1*
#324
1+
0*
#325
0+
1*
#326
1+
0*
#327
0+
1*
#328
1+
0*
#329
0+
1*
#330
1+
0*
#331
0+
1*
#332
1+
0*
b11101100 %
b11101100 /
b10000000 $
b10000000 .
1&
b11110110000101001011010100000010 -
b10000 '
b10000 1
b100 )
#333
b10000000 #
b10000000 4
0+
1*
#334
1+
0*
#335
0+
1*
#336
1+
0*
#337
0+
1*
#338
1+
0*
#339
0+
1*
#340
1+
0*
#341
0+
1*
#342
1+
0*
#343
0+
1*
#344
1+
0*
#345
0+
1*
#346
1+
0*
#347
0+
1*
#348
1+
0*
#349
0+
1*
#350
1+
0*
#351
0+
1*
#352
1+
0*
b11011110 %
b11011110 /
b11001010 $
b11001010 .
b11101111001000101000010010100001 -
b100000 '
b100000 1
b101 )
#353
b11011110 #
b11011110 4
0+
1*
#354
1+
0*
#355
0+
1*
#356
1+
0*
#357
0+
1*
#358
1+
0*
#359
0+
1*
#360
1+
0*
#361
0+
1*
#362
1+
0*
#363
0+
1*
#364
1+
0*
#365
0+
1*
#366
1+
0*
#367
0+
1*
#368
1+
0*
#369
0+
1*
#370
1+
0*
#371
0+
1*
#372
1+
0*
b1110010 %
b1110010 /
b11010010 $
b11010010 .
0&
b10111001001011010111000011101100 -
b1 '
b1 1
b11 (
b0 )
#373
0!
bz #
bz 4
0+
1*
#374
1+
0*
#375
0+
1*
#376
1+
0*
#377
0+
1*
#378
1+
0*
#379
0+
1*
#380
1+
0*
#381
0+
1*
#382
1+
0*
#383
0+
1*
#384
1+
0*
#385
0+
1*
#386
1+
0*
#387
0+
1*
#388
1+
0*
#389
0+
1*
#390
1+
0*
#391
0+
1*
#392
1+
0*
b11110000 %
b11110000 /
b1110110 $
b1110110 .
b1111000001100010111110001010011 -
b10 '
b10 1
b1 )
#393
0+
1*
#394
1+
0*
#395
0+
1*
#396
1+
0*
#397
0+
1*
#398
1+
0*
#399
0+
1*
#400
1+
0*
#401
0+
1*
#402
1+
0*
#403
0+
1*
#404
1+
0*
#405
0+
1*
#406
1+
0*
#407
0+
1*
#408
1+
0*
#409
0+
1*
#410
1+
0*
#411
0+
1*
#412
1+
0*
b11000000 %
b11000000 /
b10111111 $
b10111111 .
b1100000001000001111111000000110 -
b100 '
b100 1
b10 )
#413
0+
1*
#414
1+
0*
#415
0+
1*
#416
1+
0*
#417
0+
1*
#418
1+
0*
#419
0+
1*
#420
1+
0*
#421
0+
1*
#422
1+
0*
#423
0+
1*
#424
1+
0*
#425
0+
1*
#426
1+
0*
#427
0+
1*
#428
1+
0*
#429
0+
1*
#430
1+
0*
#431
0+
1*
#432
1+
0*
b101010 %
b101010 /
b101000 $
b101000 .
b10101011001010001000011110101 -
b1000 '
b1000 1
b11 )
#433
1!
b1010010 #
b1010010 4
0+
1*
#434
1+
0*
#435
0+
1*
#436
1+
0*
#437
0+
1*
#438
1+
0*
#439
0+
1*
#440
1+
0*
#441
0+
1*
#442
1+
0*
#443
0+
1*
#444
1+
0*
#445
0+
1*
#446
1+
0*
#447
0+
1*
#448
1+
0*
#449
0+
1*
#450
1+
0*
#451
0+
1*
#452
1+
0*
b10101100 %
b10101100 /
b1000110 $
b1000110 .
1&
b1010110010101101110111011010000 -
b10000 '
b10000 1
b100 )
#453
b100 #
b100 4
0+
1*
#454
1+
0*
#455
0+
1*
#456
1+
0*
#457
0+
1*
#458
1+
0*
#459
0+
1*
#460
1+
0*
#461
0+
1*
#462
1+
0*
#463
0+
1*
#464
1+
0*
#465
0+
1*
#466
1+
0*
#467
0+
1*
#468
1+
0*
#469
0+
1*
#470
1+
0*
#471
0+
1*
